mlvtk/__init__.py
mlvtk/base/Vmodel.py
mlvtk/base/__init__.py
mlvtk/base/callbacks/CheckpointCallback.py
mlvtk/base/callbacks/__init__.py
mlvtk/base/normalize/FilterNorm.py
mlvtk/base/normalize/TrajectoryCalculator.py
mlvtk/base/normalize/__init__.py
mlvtk/base/plot/__init__.py
mlvtk/base/plot/plotter.py
mlvtk/base/pytest.ini
mlvtk-1.0.3.dist-info/LICENSE.txt
mlvtk-1.0.3.dist-info/WHEEL
mlvtk-1.0.3.dist-info/METADATA
mlvtk-1.0.3.dist-info/RECORD
