Metadata-Version: 2.1
Name: mlvtk
Version: 1.0.3
Summary: loss surface visualization tool
License: MIT
Author: tm-schwartz
Author-email: tschwartz@csumb.edu
Requires-Python: >=3.6.1,<4.0.0
Classifier: Intended Audience :: Education
Classifier: Intended Audience :: Science/Research
Classifier: License :: OSI Approved :: MIT License
Classifier: Programming Language :: Python :: 3
Classifier: Programming Language :: Python :: 3.7
Classifier: Programming Language :: Python :: 3.8
Classifier: Programming Language :: Python :: 3.9
Classifier: Topic :: Education
Classifier: Topic :: Scientific/Engineering :: Artificial Intelligence
Classifier: Topic :: Scientific/Engineering :: Visualization
Requires-Dist: h5py (>=2.10.0,<2.11.0)
Requires-Dist: pandas (>=1.1.3,<1.2.0)
Requires-Dist: plotly (>=4.9.0)
Requires-Dist: scikit-learn (>=0.23.2,<0.24.0)
Requires-Dist: tensorflow (>=2.3.2,<2.4.2)
Requires-Dist: tqdm (>=4.50.2,<4.51.0)
